sentry_yach/__init__.py
sentry_yach/plugin.py
sentry_yach-0.0.5.dist-info/LICENSE
sentry_yach-0.0.5.dist-info/METADATA
sentry_yach-0.0.5.dist-info/WHEEL
sentry_yach-0.0.5.dist-info/entry_points.txt
sentry_yach-0.0.5.dist-info/top_level.txt
sentry_yach-0.0.5.dist-info/RECORD
