Metadata-Version: 2.1
Name: sentry-yach
Version: 0.0.5
Summary: A Sentry extension which send errors stats to yach
Home-page: https://github.com/qingchunyibeifangzongle/sentry-yach
Author: yp
Author-email: xiaoyueueyue0612@gmail.com
License: MIT
Keywords: sentry yach
Platform: UNKNOWN
Classifier: Programming Language :: Python :: 2.7
Classifier: License :: OSI Approved :: MIT License
Requires-Dist: sentry (>=9.0.0)
